cli/__init__.py
cli/_compat.py
cli/commands/__init__.py
cli/commands/add/__init__.py
cli/commands/add/all.py
cli/commands/add/domain.py
cli/commands/add/module.py
cli/commands/add/resource.py
cli/commands/add.py
cli/commands/checkpoint.py
cli/commands/create.py
cli/commands/dev/__init__.py
cli/commands/dev/dev_app.py
cli/commands/dev/modules.py
cli/commands/diff.py
cli/commands/doctor.py
cli/commands/frameworks.py
cli/commands/info.py
cli/commands/init.py
cli/commands/license.py
cli/commands/list.py
cli/commands/merge.py
cli/commands/migrate.py
cli/commands/module_gating.py
cli/commands/modules.py
cli/commands/optimize.py
cli/commands/project.py
cli/commands/reconcile.py
cli/commands/rollback.py
cli/commands/snapshot.py
cli/commands/uninstall.py
cli/commands/upgrade.py
cli/commands/version.py
cli/global_cli.py
cli/main.py
cli/py.typed
cli/ui/__init__.py
cli/ui/printer.py
cli/utils/__init__.py
cli/utils/classifier.py
cli/utils/env_schema_utils.py
cli/utils/filesystem.py
cli/utils/module_scaffold.py
cli/utils/module_structure_cli.py
cli/utils/module_validation.py
cli/utils/pathing.py
cli/utils/prompts.py
cli/utils/registry.py
cli/utils/scaffold/__init__.py
cli/utils/scaffold/blueprints.py
cli/utils/scaffold/constants.py
cli/utils/scaffold/identifiers.py
cli/utils/scaffold/result.py
cli/utils/scaffold/templates/__init__.py
cli/utils/scaffold/templates/documentation.py
cli/utils/scaffold/templates/module_files.py
cli/utils/scaffold/templates/repository_tests.py
cli/utils/validators.py
cli/utils/variables_prompt.py
core/__init__.py
core/config/__init__.py
core/config/kit_config.py
core/config/version.py
core/distribution.json
core/engine/__init__.py
core/engine/dependency_installer.py
core/engine/generator.py
core/engine/module_installer.py
core/engine/registry.py
core/exceptions.py
core/frameworks/__init__.py
core/frameworks/base.py
core/frameworks/django_adapter.py
core/frameworks/fastapi_adapter.py
core/hooks/__init__.py
core/hooks/framework_handlers.py
rapidkit_core-0.2.1rc1.dist-info/METADATA
rapidkit_core-0.2.1rc1.dist-info/WHEEL
rapidkit_core-0.2.1rc1.dist-info/entry_points.txt
rapidkit_core-0.2.1rc1.dist-info/licenses/LICENSE
rapidkit_core-0.2.1rc1.dist-info/RECORD
